apmpythonpackage/__init__.py
apmpythonpackage/apmpythonpackage.py
apmpython-0.1.11.dist-info/LICENSE
apmpython-0.1.11.dist-info/METADATA
apmpython-0.1.11.dist-info/WHEEL
apmpython-0.1.11.dist-info/top_level.txt
apmpython-0.1.11.dist-info/RECORD
